transunion/__init__.py
transunion/api.py
transunion/configuration.py
transunion/errors.py
transunion/request.py
transunion/response.py
transunion/settings.py
transunion/utils/__init__.py
transunion/utils/xml.py
transunion/utils/xml_convert.py
transunion-0.1.0.dist-info/DESCRIPTION.rst
transunion-0.1.0.dist-info/METADATA
transunion-0.1.0.dist-info/RECORD
transunion-0.1.0.dist-info/WHEEL
transunion-0.1.0.dist-info/metadata.json
transunion-0.1.0.dist-info/top_level.txt
